pylicenses/__init__.py
pylicenses/__main__.py
pylicenses/providers/__init__.py
pylicenses/providers/condachannel.py
pylicenses/providers/condalocal.py
pylicenses/providers/piplocal.py
pylicenses/providers/pypi.py
pylicenses/providers/static.py
pylicenses/tests/__init__.py
pylicenses/tests/test_pylicense.py
pylicenses-0.1.dist-info/LICENSE
pylicenses-0.1.dist-info/METADATA
pylicenses-0.1.dist-info/WHEEL
pylicenses-0.1.dist-info/top_level.txt
pylicenses-0.1.dist-info/RECORD
