Metadata-Version: 2.1
Name: pylicenses
Version: 0.1
Summary: License scanning and documentation for conda and pip envs
Home-page: https://github.com/miraculixx/pylicenses
Author: Patrick Senti
Author-email: patrick.senti@productaize.io
License: MIT
Platform: UNKNOWN
Classifier: License :: OSI Approved :: Apache Software License
Classifier: Programming Language :: Python
Classifier: Programming Language :: Python :: 3
Classifier: Programming Language :: Python :: 3.6
Classifier: Programming Language :: Python :: Implementation :: CPython
Requires-Dist: sh (==1.12.14)
Requires-Dist: requests (==2.21.0)
Requires-Dist: tabulate (==0.8.2)
